asynctaskgraph/__init__.py
asynctaskgraph-0.0.7.dist-info/LICENSE
asynctaskgraph-0.0.7.dist-info/METADATA
asynctaskgraph-0.0.7.dist-info/WHEEL
asynctaskgraph-0.0.7.dist-info/top_level.txt
asynctaskgraph-0.0.7.dist-info/RECORD
